README.md
setup.py
mapsku/__init__.py
mapsku/calculate_distance.py
mapsku/calculate_total_distance.py
mapsku/degrees_to_radians.py
mapsku/distance_to_center.py
mapsku/estimate_travel_time.py
mapsku/filter_by_radius.py
mapsku/find_nearest_point.py
mapsku/km_to_m.py
mapsku.egg-info/PKG-INFO
mapsku.egg-info/SOURCES.txt
mapsku.egg-info/dependency_links.txt
mapsku.egg-info/requires.txt
mapsku.egg-info/top_level.txt