Metadata-Version: 2.1
Name: mapsku
Version: 1.0
Summary: Package untuk perhitungan jarak dan fungsi sistem koordinat geografis
Home-page: https://github.com/Ryannfirmansyah/Perhitungan_jarak_dan_sistem_koordinat.git
Author: Kelompok 1 Algoritma & Pemrograman B
Classifier: Programming Language :: Python :: 3
Classifier: License :: OSI Approved :: MIT License
Classifier: Operating System :: OS Independent
Requires-Python: >=3.6
Requires-Dist: geopy
Requires-Dist: numpy
